plain/importmap/README.md
plain/importmap/__init__.py
plain/importmap/cli.py
plain/importmap/core.py
plain/importmap/generator.py
plain/importmap/templates.py
plain/importmap/templates/importmap/js.html
plain_importmap-0.8.1.dist-info/METADATA
plain_importmap-0.8.1.dist-info/WHEEL
plain_importmap-0.8.1.dist-info/licenses/LICENSE
plain_importmap-0.8.1.dist-info/RECORD
