Metadata-Version: 2.4
Name: plain.importmap
Version: 0.8.1
Summary: JavaScript import maps for Plain.
Author-email: Dave Gaeddert <dave.gaeddert@dropseed.dev>
License-Expression: BSD-3-Clause
License-File: LICENSE
Requires-Python: >=3.11
Requires-Dist: marshmallow>=3.14.1
Requires-Dist: plain<1.0.0
Requires-Dist: requests>=2.0.0
Requires-Dist: tomli>=2.0.0
